spider_lib/__init__.py
spider_lib/spider.py
spider_lib/spider_demo.py
spider_lib-0.0.0.4.dist-info/METADATA
spider_lib-0.0.0.4.dist-info/WHEEL
spider_lib-0.0.0.4.dist-info/top_level.txt
spider_lib-0.0.0.4.dist-info/RECORD
